kipjak/__init__.py
kipjak/bind_type.py
kipjak/command_line.py
kipjak/command_startup.py
kipjak/convert_memory.py
kipjak/convert_signature.py
kipjak/convert_type.py
kipjak/countdown_timer.py
kipjak/disk_storage.py
kipjak/edit_role.py
kipjak/file_object.py
kipjak/folder_object.py
kipjak/general_purpose.py
kipjak/get_local_ip.py
kipjak/get_response.py
kipjak/head_lock.py
kipjak/home_role.py
kipjak/http.py
kipjak/ip_networking.py
kipjak/json_codec.py
kipjak/listen_connect.py
kipjak/log_agent.py
kipjak/make_message.py
kipjak/message_memory.py
kipjak/message_pump.py
kipjak/noop_codec.py
kipjak/object_collector.py
kipjak/object_directory.py
kipjak/object_logs.py
kipjak/object_runtime.py
kipjak/object_space.py
kipjak/object_spool.py
kipjak/object_startup.py
kipjak/parsetab.py
kipjak/platform_system.py
kipjak/point_machine.py
kipjak/point_runtime.py
kipjak/process_directory.py
kipjak/process_object.py
kipjak/retry_intervals.py
kipjak/rolling_log.py
kipjak/routine_point.py
kipjak/running_routine.py
kipjak/virtual_codec.py
kipjak/virtual_memory.py
kipjak/virtual_point.py
kipjak/virtual_runtime.py
kipjak/xml_codec.py
kipjak-1.0.27.dist-info/licenses/LICENSE
script/group_jak.py
script/host_jak.py
script/kipjak.py
script/lan_jak.py
kipjak-1.0.27.dist-info/METADATA
kipjak-1.0.27.dist-info/WHEEL
kipjak-1.0.27.dist-info/entry_points.txt
kipjak-1.0.27.dist-info/top_level.txt
kipjak-1.0.27.dist-info/RECORD
